deduplicate/deduplicate.py
deduplicate-0.1.0.dist-info/LICENSE
deduplicate-0.1.0.dist-info/METADATA
deduplicate-0.1.0.dist-info/WHEEL
deduplicate-0.1.0.dist-info/entry_points.txt
deduplicate-0.1.0.dist-info/top_level.txt
deduplicate-0.1.0.dist-info/RECORD
