Metadata-Version: 2.1
Name: deduplicate
Version: 0.1.0
Summary: Duplicate line removal plug-in for vpype
Home-page: https://github.com/LoicGoulefert/deduplicate
Author: Loïc Goulefert
License: MIT License        
Platform: UNKNOWN
Classifier: Development Status :: 4 - Beta
Classifier: License :: OSI Approved :: MIT License
Classifier: Topic :: Multimedia :: Graphics
Classifier: Environment :: Plugins
License-File: LICENSE
Requires-Dist: click
Requires-Dist: numpy
Requires-Dist: shapely (>=1.8.0)
Requires-Dist: vpype (<2.0,>=1.9)
Requires-Dist: tqdm (>=4.61.1)
